github_ssh_key/__init__.py
github_ssh_key/app.py
github_ssh_key/commander.py
github_ssh_key/manager.py
github_ssh_key-0.4.2.dist-info/licenses/LICENSE
github_ssh_key-0.4.2.dist-info/METADATA
github_ssh_key-0.4.2.dist-info/WHEEL
github_ssh_key-0.4.2.dist-info/entry_points.txt
github_ssh_key-0.4.2.dist-info/top_level.txt
github_ssh_key-0.4.2.dist-info/RECORD
