Metadata-Version: 2.4
Name: github-ssh-key
Version: 0.4.2
Summary: GitHub ssh key manager. Console utility for creating, getting, testing, using public ssh keys for GitHub.
Home-page: https://github.com/smartlegionlab/github-ssh-key/
Author: A.A. Suvorov
Author-email: smartlegiondev@gmail.com
License: BSD 3-Clause License
Project-URL: Documentation, https://github.com/smartlegionlab/github-ssh-keyn/blob/master/README.md
Project-URL: Release notes, https://github.com/smartlegionlab/github-ssh-key/releases
Keywords: github,github ssh,github ssh create key,github ssh test key,github clone with ssh,smart legion,smart legion lab
Classifier: Development Status :: 5 - Production/Stable
Classifier: Environment :: Console
Classifier: Intended Audience :: End Users/Desktop
Classifier: Intended Audience :: System Administrators
Classifier: License :: OSI Approved :: BSD License
Classifier: Natural Language :: English
Classifier: Operating System :: OS Independent
Classifier: Operating System :: Microsoft :: Windows
Classifier: Operating System :: POSIX :: Linux
Classifier: Programming Language :: Python :: 3 :: Only
Classifier: Topic :: Software Development :: Libraries :: Python Modules
Classifier: Topic :: Utilities
Requires-Python: >=3.6
License-File: LICENSE
Requires-Dist: click~=8.0.1
Requires-Dist: smartcliapp~=0.4.0
Dynamic: license-file
